{
 "version": "auto-py-to-exe-configuration_v1",
 "pyinstallerOptions": [
  {
   "optionDest": "noconfirm",
   "value": true
  },
  {
   "optionDest": "filenames",
   "value": "D:/JetBrainsProject/PycharmProjects/NetworkCalculator/src/main.py"
  },
  {
   "optionDest": "onefile",
   "value": false
  },
  {
   "optionDest": "console",
   "value": false
  },
  {
   "optionDest": "name",
   "value": "NetworkCalculator"
  },
  {
   "optionDest": "clean_build",
   "value": false
  },
  {
   "optionDest": "loglevel",
   "value": "DEBUG"
  },
  {
   "optionDest": "strip",
   "value": false
  },
  {
   "optionDest": "noupx",
   "value": false
  },
  {
   "optionDest": "disable_windowed_traceback",
   "value": false
  },
  {
   "optionDest": "uac_admin",
   "value": false
  },
  {
   "optionDest": "uac_uiaccess",
   "value": false
  },
  {
   "optionDest": "argv_emulation",
   "value": false
  },
  {
   "optionDest": "bootloader_ignore_signals",
   "value": false
  },
  {
   "optionDest": "datas",
   "value": "D:/JetBrainsProject/PycharmProjects/NetworkCalculator/src/ip_calc.py;."
  },
  {
   "optionDest": "datas",
   "value": "D:/JetBrainsProject/PycharmProjects/NetworkCalculator/src/networkcalculator.kv;."
  }
 ],
 "nonPyinstallerOptions": {
  "increaseRecursionLimit": true,
  "manualArguments": ""
 }
}